redmine_client/__init__.py
redmine_client/async_client.py
redmine_client/client.py
redmine_client/exceptions.py
redmine_client/models.py
redmine_client-0.1.0.dist-info/METADATA
redmine_client-0.1.0.dist-info/WHEEL
redmine_client-0.1.0.dist-info/licenses/LICENSE
redmine_client-0.1.0.dist-info/RECORD
